{
  "@class" : "se.inera.intyg.common.integration.hsa.model.Vardgivare",
  "id" : "TSTNMT2321000156-1061",
  "namn" : "VårdgivareCambio",
  "vardenheter" : [
    {
      "@class" : "se.inera.intyg.common.integration.hsa.model.Vardenhet",
      "id" : "TSTNMT2321000156-1062",
      "namn" : "CambioVårdenhet1",
      "epost" : "enhet1@cambio.invalid.se",
      "telefonnummer" : "0101231567897",
      "postadress" : "Cambio gata 1",
      "postnummer" : "12345",
      "postort" : "Cambiostad",
      "arbetsplatskod" : "2234567890"
    },
    {
      "@class" : "se.inera.intyg.common.integration.hsa.model.Vardenhet",
      "id" : "TSTNMT2321000156-1063",
      "namn" : "CambioVårdenhet2",
      "epost" : "enhet2@cambio.invalid.se",
      "telefonnummer" : "0101112131416",
      "postadress" : "Cambio gata 2",
      "postnummer" : "12345",
      "postort" : "Cambiostad",
      "arbetsplatskod" : "2234567891"
    }
  ]
}
